zzdeeprollover/__init__.py
zzdeeprollover/addAlternativePathToOriginalVideo.py
zzdeeprollover/cleanFolders.py
zzdeeprollover/createInitialImages.py
zzdeeprollover/createTrainOrTestDataset.py
zzdeeprollover/createValidationVideo.py
zzdeeprollover/dataTransformationAugmentations.py
zzdeeprollover/detectRolloverFrames.py
zzdeeprollover/imageTransformFunctions.py
zzdeeprollover/learnModel.py
zzdeeprollover/seq_to_avi.py
zzdeeprollover/version.txt
zzdeeprollover/zzVideoReading.py
zzdeeprollover-0.0.9.data/data/zzdeeprollover/version.txt
zzdeeprollover-0.0.9.dist-info/LICENSE
zzdeeprollover-0.0.9.dist-info/METADATA
zzdeeprollover-0.0.9.dist-info/WHEEL
zzdeeprollover-0.0.9.dist-info/top_level.txt
zzdeeprollover-0.0.9.dist-info/RECORD
