Metadata-Version: 2.1
Name: zzdeeprollover
Version: 0.0.9
Summary: Detect rollovers in zebrafish larvae
Home-page: https://github.com/oliviermirat/ZZDeepRollover
Download-URL: https://github.com/oliviermirat/ZZDeepRollover/releases/latest
Author: Olivier Mirat
Author-email: olivier.mirat.om@gmail.com
License: AGPL-3.0
Keywords: Animal,Behavior,Tracking,Zebrafish,Deep Learning,Rolling
Classifier: Programming Language :: Python :: 3
License-File: LICENSE
Requires-Dist: scikit-learn
Requires-Dist: torch
Requires-Dist: numpy
Requires-Dist: matplotlib
Requires-Dist: torchvision
Requires-Dist: pandas
Requires-Dist: pillow
Requires-Dist: opencv-python-headless
